opendataframework/README.md
opendataframework/__init__.py
opendataframework/__main__.py
opendataframework/analytics/setup.sh
opendataframework/analytics/superset/.env
opendataframework/analytics/superset/Dockerfile
opendataframework/analytics/superset/database/postgres/create.sh
opendataframework/analytics/superset/database/postgres/setup.sh
opendataframework/analytics/superset/docker-compose.yaml
opendataframework/analytics/superset/setup.sh
opendataframework/api/api-postgres/.env
opendataframework/api/api-postgres/Dockerfile
opendataframework/api/api-postgres/app/__init__.py
opendataframework/api/api-postgres/app/config.py
opendataframework/api/api-postgres/app/crud.py
opendataframework/api/api-postgres/app/database.py
opendataframework/api/api-postgres/app/dependencies.py
opendataframework/api/api-postgres/app/main.py
opendataframework/api/api-postgres/app/models.py
opendataframework/api/api-postgres/app/router.py
opendataframework/api/api-postgres/docker-compose.yaml
opendataframework/api/api-postgres/poetry.lock
opendataframework/api/api-postgres/pyproject.toml
opendataframework/api/inference/.env
opendataframework/api/inference/Dockerfile
opendataframework/api/inference/app/__init__.py
opendataframework/api/inference/app/config.py
opendataframework/api/inference/app/crud.py
opendataframework/api/inference/app/dependencies.py
opendataframework/api/inference/app/main.py
opendataframework/api/inference/app/models.py
opendataframework/api/inference/app/router.py
opendataframework/api/inference/docker-compose.yaml
opendataframework/api/inference/pyproject.toml
opendataframework/api/ingest.py
opendataframework/api/requirements.txt
opendataframework/api/setup.sh
opendataframework/devcontainers/R/.devcontainer/.Rprofile
opendataframework/devcontainers/R/.devcontainer/Dockerfile
opendataframework/devcontainers/R/.devcontainer/devcontainer.json
opendataframework/devcontainers/python/.devcontainer/Dockerfile
opendataframework-0.0.4.dist-info/LICENSE
opendataframework-0.0.4.dist-info/WHEEL
opendataframework-0.0.4.dist-info/entry_points.txt
opendataframework-0.0.4.dist-info/METADATA
opendataframework-0.0.4.dist-info/RECORD
